Desktop/lm32_soc_hdl/rtl/wb_BCD/selector_anodes.v
module selector_anodes
	(
	 input clk,
	 input [3:0] valor1, valor2, valor3, valor4,	
	 output reg [3:0] valanode,
	 output reg [3:0] outvalsseg
	);
	
	reg [25:0] counter;
	reg [1:0] sel;
	reg clk1;
	initial begin counter=0; sel=0; clk1=0; end

	always @(posedge clk)
	if (counter==50000) begin
		counter=0; clk1=~clk1;
			end
	else begin
		counter=counter+1;
			end

	always @(posedge clk1)
	begin
	sel=sel+1;
	if (sel==4) begin
		sel=0;
	end		
		case(sel)
			3'd0: valanode = 4'b1110; 
			3'd1: valanode = 4'b1101;
			3'd2: valanode = 4'b1011;
			default: valanode = 4'b0111;
		endcase

		case(valanode)
			4'b1110: outvalsseg = valor1;
			4'b1101: outvalsseg = valor2;
			4'b1011: outvalsseg = valor3;
			default: outvalsseg = valor4;
		endcase
	end

endmodule

Desktop/lm32_soc_hdl/rtl/wb_BCD/decoder_segments.v
module decoder_segments 
	(
	 input [3:0] dec,
	 output reg [6:0] sseg 
	);
	
	always @(dec)
	case(dec)
	
	4'b0000: sseg = 7'b0000001; // 0
	4'b0001: sseg = 7'b1001111; // 1
	4'b0010: sseg = 7'b0010010; // 2
	4'b0011: sseg = 7'b0000110; // 3
	4'b0100: sseg = 7'b1001100; // 4
	4'b0101: sseg = 7'b0100100; // 5
	4'b0110: sseg = 7'b0100000; // 6
	4'b0111: sseg = 7'b0001111; // 7
	4'b1000: sseg = 7'b0000000; // 8
	4'b1001: sseg = 7'b0000100; // 9
	4'b1010: sseg = 7'b0001000; // A	
	4'b1011: sseg = 7'b1100000; // B
	4'b1100: sseg = 7'b0110001; // C
	4'b1101: sseg = 7'b1000010; // D
	4'b1110: sseg = 7'b0110000; // E
	//4'b1111: sseg = 7'b0111000; // F
	default: sseg = 7'b1111111; // NULL
	endcase
endmodule

Desktop/lm32_soc_hdl/rtl/wb_BCD/BCD.v
`timescale 1ns / 1ps

module BCD(
		input clk,		
		input [3:0] dato1,
		input [3:0] dato2,
		input [3:0] dato3,
		input [3:0] dato4,
		output [6:0] seg,
		output [3:0] an
);

wire [3:0] dato_wire;
wire [3:0] dato_in1;
wire [3:0] dato_in2;
wire [3:0] dato_in3;
wire [3:0] dato_in4;

decoder_segments decoder_segments
	(
	.sseg(seg),
	.dec(dato_wire)
	);

selector_anodes selector_anodes
	(
	.clk(clk),
	.valor1(dato_in1),
	.valor2(dato_in2),
	.valor3(dato_in3),
	.valor4(dato_in4),
	.valanode(an),
	.outvalsseg(dato_wire)
	);

assign dato_in1 = dato1;
assign dato_in2 = dato2;
assign dato_in3 = dato3;
assign dato_in4 = dato4;

endmodule

Desktop/lm32_soc_hdl/rtl/wb_BCD/wb_BCD.v
//---------------------------------------------------------------------------
// Wishbone General Pupose IO Component
//
//     0x00	
//     
//     0x14     number   (read/write)
//    
//
//---------------------------------------------------------------------------

module wb_BCD (
	input              clk,
	input              reset,
	// Wishbone interface
	input              wb_stb_i,
	input              wb_cyc_i,
	output             wb_ack_o,
	input              wb_we_i,
	input       [31:0] wb_adr_i,
	input        [3:0] wb_sel_i,
	input       [31:0] wb_dat_i,
	output reg  [31:0] wb_dat_o,
	output [6:0] seg_out,
	output [3:0] an_out
);

//---------------------------------------------------------------------------
// 
//---------------------------------------------------------------------------

wire [31:0] BCDcr = 32'b0;

wire [6:0] seg0;
wire [3:0] an0;
reg [3:0] dato1;
reg [3:0] dato2;
reg [3:0] dato3;
reg [3:0] dato4;

BCD bcd0 (
	.clk(clk),
	.dato1(dato1),
	.dato2(dato2),
	.dato3(dato3),
	.dato4(dato4),
	.seg(seg0),
	.an(an0)
);


// Wishbone
reg  ack;
assign wb_ack_o = wb_stb_i & wb_cyc_i & ack;

wire wb_rd = wb_stb_i & wb_cyc_i & ~wb_we_i;
wire wb_wr = wb_stb_i & wb_cyc_i &  wb_we_i;



always @(posedge clk)
begin
	if (reset) begin
		ack      <= 0;
dato1<=15;
dato2<=15;
dato3<=15;
dato4<=15;

		
	end else begin
		// Handle WISHBONE access
		ack    <= 0;

		if (wb_wr & ~ack ) begin // write cycle
			ack <= 1;

			case (wb_adr_i[3:2])
			2'b00: dato1 <= wb_dat_i[3:0];	//wb_dat_i		
			2'b01: dato2 <= wb_dat_i[3:0];			
			2'b10: dato3 <= wb_dat_i[3:0];			
			2'b11: dato4 <= wb_dat_i[3:0];			
			endcase
		end
	end
end


assign an_out = an0;
assign seg_out = seg0;


endmodule

Desktop/lm32_soc_hdl/rtl/wb_BCD/wb_BCD_tb.v
`timescale 1ns / 1ps

`define SIMULATION


module wb_BCD_tb;

  
   reg clk;
   reg  reset;
	// Wishbone interface
	reg              bcd0_stb;
	reg              bcd0_cyc;
	wire             bcd0_ack;
	reg              bcd0_we;
	reg       [31:0] bcd0_adr;
	reg        [3:0] bcd0_sel;
	reg       [31:0] bcd0_dat;	
        wire  [31:0] wb_dat_o;
	wire [6:0] seg_out;
	wire [3:0] an_out;

  wb_BCD uut (
	.clk(      clk          ),
	.reset(    reset          ),
	//
	.wb_adr_i( bcd0_adr    ),
	.wb_dat_i( bcd0_dat  ),
	.wb_stb_i( bcd0_stb    ),
	.wb_cyc_i( bcd0_cyc    ),
	.wb_we_i(  bcd0_we     ),
	.wb_ack_o( bcd0_ack    ), 
	.wb_sel_i( bcd0_sel    ),
        .wb_dat_o(wb_dat_o),
	.seg_out(seg_out),
	.an_out(an_out)
	
);


   parameter PERIOD          = 20;
   parameter real DUTY_CYCLE = 0.5;
   parameter OFFSET          = 0;
   reg [20:0] i;
   event reset_trigger;




   initial begin  // Initialize Inputs
      clk = 0; reset = 1; 
   end

   initial  begin  // Process for clk
     #OFFSET;
     forever
       begin
         clk = 1'b0;
         #(PERIOD-(PERIOD*DUTY_CYCLE)) clk = 1'b1;
         #(PERIOD*DUTY_CYCLE);
       end
   end

   initial begin // Reset the system, Start the image capture process
      forever begin 
        @ (reset_trigger);
 
				// stimulus here

       for(i=0; i<4; i=i+1) begin
         @ (posedge clk);
       end

	bcd0_adr = 32'h04;	
	bcd0_dat = 32'd7;
	reset=0;
	bcd0_stb=1; bcd0_cyc=1; bcd0_we=1;
	

       for(i=0; i<4; i=i+1) begin
         @ (posedge clk);
       end

	
	bcd0_adr = 32'h00;	
	bcd0_dat = 32'd3;
	reset=0;
	bcd0_stb=1; bcd0_cyc=1; bcd0_we=1;
	
  
       for(i=0; i<4; i=i+1) begin
         @ (posedge clk);
       end


      end
   end
	 

   initial begin: TEST_CASE
     $dumpfile("wb_BCD_tb.vcd");
     $dumpvars(-1, uut);
	
     #10 -> reset_trigger;
     #((PERIOD*DUTY_CYCLE)*2000000) $finish;
   end

endmodule

Desktop/lm32_soc_hdl/rtl/wb_BCD/peripheral_mult_TB.vcd
$date
	Wed May  4 13:14:16 2016
$end
$version
	Icarus Verilog
$end
$timescale
	1ps
$end
$scope module wb_BCD_tb $end
$scope module uut $end
$var wire 32 ! BCDcr [31:0] $end
$var wire 4 " an0 [3:0] $end
$var wire 4 # an_out [3:0] $end
$var wire 1 $ clk $end
$var wire 1 % reset $end
$var wire 7 & seg0 [6:0] $end
$var wire 7 ' seg_out [6:0] $end
$var wire 1 ( wb_ack_o $end
$var wire 32 ) wb_adr_i [31:0] $end
$var wire 1 * wb_cyc_i $end
$var wire 32 + wb_dat_i [31:0] $end
$var wire 1 , wb_rd $end
$var wire 4 - wb_sel_i [3:0] $end
$var wire 1 . wb_stb_i $end
$var wire 1 / wb_we_i $end
$var wire 1 0 wb_wr $end
$var reg 1 1 ack $end
$var reg 4 2 dato1 [3:0] $end
$var reg 4 3 dato2 [3:0] $end
$var reg 4 4 dato3 [3:0] $end
$var reg 4 5 dato4 [3:0] $end
$var reg 32 6 wb_dat_o [31:0] $end
$scope module bcd0 $end
$var wire 4 7 an [3:0] $end
$var wire 1 $ clk $end
$var wire 4 8 dato1 [3:0] $end
$var wire 4 9 dato2 [3:0] $end
$var wire 4 : dato3 [3:0] $end
$var wire 4 ; dato4 [3:0] $end
$var wire 4 < dato_in1 [3:0] $end
$var wire 4 = dato_in2 [3:0] $end
$var wire 4 > dato_in3 [3:0] $end
$var wire 4 ? dato_in4 [3:0] $end
$var wire 4 @ dato_wire [3:0] $end
$var wire 7 A seg [6:0] $end
$scope module decoder_segments $end
$var wire 4 B dec [3:0] $end
$var reg 7 C sseg [6:0] $end
$upscope $end
$scope module selector_anodes $end
$var wire 1 $ clk $end
$var wire 4 D valor1 [3:0] $end
$var wire 4 E valor2 [3:0] $end
$var wire 4 F valor3 [3:0] $end
$var wire 4 G valor4 [3:0] $end
$var reg 1 H clk1 $end
$var reg 26 I counter [25:0] $end
$var reg 4 J outvalsseg [3:0] $end
$var reg 2 K sel [1:0] $end
$var reg 4 L valanode [3:0] $end
$upscope $end
$upscope $end
$upscope $end
$upscope $end
$enddefinitions $end
#0
$dumpvars
bx L
b0 K
bx J
b0 I
0H
bx G
bx F
bx E
bx D
bx C
bx B
bx A
bx @
bx ?
bx >
bx =
bx <
bx ;
bx :
bx 9
bx 8
bx 7
bx 6
bx 5
bx 4
bx 3
bx 2
x1
x0
x/
x.
bx -
x,
bx +
x*
bx )
x(
bx '
bx &
1%
0$
bx #
bx "
b0 !
$end
#10000
0(
01
b1 I
1$
#20000
0$
#30000
b10 I
1$
#40000
0$
#50000
b11 I
1$
#60000
0$
#70000
b100 I
1$
#80000
0$
#90000
0,
10
b101 I
1/
1*
1.
b101 +
b0 )
1$
#100000
0$
#110000
b110 I
1$
#120000
0$
#130000
b111 I
1$
#140000
0$
#150000
b1000 I
1$
#160000
0$
#170000
b1001 I
1$
#180000
0$
#190000
b1010 I
1$
#200000
0$
#210000
b1011 I
1$
#220000
0$
#230000
b1100 I
1$
#240000
0$
#250000
b1101 I
1$
#260000
0$
#270000
b1110 I
1$
#280000
0$
#290000
b1111 I
1$
#300000
0$
#310000
b10000 I
1$
#320000
0$
#330000
b10001 I
1$
#340000
0$
#350000
b10010 I
1$
#360000
0$
#370000
b10011 I
1$
#380000
0$
#390000
b10100 I
1$
#400000
0$
#410000
b10101 I
1$
#420000
0$
#430000
b10110 I
1$
#440000
0$
#450000
b10111 I
1$
#460000
0$
#470000
b11000 I
1$
#480000
0$
#490000
b11001 I
1$
#500000
0$
#510000
b11010 I
1$
#520000
0$
#530000
b11011 I
1$
#540000
0$
#550000
b11100 I
1$
#560000
0$
#570000
b11101 I
1$
#580000
0$
#590000
b11110 I
1$
#600000
0$
#610000
b11111 I
1$
#620000
0$
#630000
b100000 I
1$
#640000
0$
#650000
b100001 I
1$
#660000
0$
#670000
b100010 I
1$
#680000
0$
#690000
b100011 I
1$
#700000
0$
#710000
b100100 I
1$
#720000
0$
#730000
b100101 I
1$
#740000
0$
#750000
b100110 I
1$
#760000
0$
#770000
b100111 I
1$
#780000
0$
#790000
b101000 I
1$
#800000
0$
#810000
b101001 I
1$
#820000
0$
#830000
b101010 I
1$
#840000
0$
#850000
b101011 I
1$
#860000
0$
#870000
b101100 I
1$
#880000
0$
#890000
b101101 I
1$
#900000
0$
#910000
b101110 I
1$
#920000
0$
#930000
b101111 I
1$
#940000
0$
#950000
b110000 I
1$
#960000
0$
#970000
b110001 I
1$
#980000
0$
#990000
b110010 I
1$
#1000000
0$
#1010000
b110011 I
1$
#1020000
0$
#1030000
b110100 I
1$
#1040000
0$
#1050000
b110101 I
1$
#1060000
0$
#1070000
b110110 I
1$
#1080000
0$
#1090000
b110111 I
1$
#1100000
0$
#1110000
b111000 I
1$
#1120000
0$
#1130000
b111001 I
1$
#1140000
0$
#1150000
b111010 I
1$
#1160000
0$
#1170000
b111011 I
1$
#1180000
0$
#1190000
b111100 I
1$
#1200000
0$
#1210000
b111101 I
1$
#1220000
0$
#1230000
b111110 I
1$
#1240000
0$
#1250000
b111111 I
1$
#1260000
0$
#1270000
b1000000 I
1$
#1280000
0$
#1290000
b1000001 I
1$
#1300000
0$
#1310000
b1000010 I
1$
#1320000
0$
#1330000
b1000011 I
1$
#1340000
0$
#1350000
b1000100 I
1$
#1360000
0$
#1370000
b1000101 I
1$
#1380000
0$
#1390000
b1000110 I
1$
#1400000
0$
#1410000
b1000111 I
1$
#1420000
0$
#1430000
b1001000 I
1$
#1440000
0$
#1450000
b1001001 I
1$
#1460000
0$
#1470000
b1001010 I
1$
#1480000
0$
#1490000
b1001011 I
1$
#1500000
0$
#1510000
b1001100 I
1$
#1520000
0$
#1530000
b1001101 I
1$
#1540000
0$
#1550000
b1001110 I
1$
#1560000
0$
#1570000
b1001111 I
1$
#1580000
0$
#1590000
b1010000 I
1$
#1600000
0$
#1610000
b1010001 I
1$
#1620000
0$
#1630000
b1010010 I
1$
#1640000
0$
#1650000
b1010011 I
1$
#1660000
0$
#1670000
b1010100 I
1$
#1680000
0$
#1690000
b1010101 I
1$
#1700000
0$
#1710000
b1010110 I
1$
#1720000
0$
#1730000
b1010111 I
1$
#1740000
0$
#1750000
b1011000 I
1$
#1760000
0$
#1770000
b1011001 I
1$
#1780000
0$
#1790000
b1011010 I
1$
#1800000
0$
#1810000
b1011011 I
1$
#1820000
0$
#1830000
b1011100 I
1$
#1840000
0$
#1850000
b1011101 I
1$
#1860000
0$
#1870000
b1011110 I
1$
#1880000
0$
#1890000
b1011111 I
1$
#1900000
0$
#1910000
b1100000 I
1$
#1920000
0$
#1930000
b1100001 I
1$
#1940000
0$
#1950000
b1100010 I
1$
#1960000
0$
#1970000
b1100011 I
1$
#1980000
0$
#1990000
b1100100 I
1$
#2000000
0$
#2010000
b1100101 I
1$
